{"cameraMode":{"drawMode":0,"name":"Shaded","section":"Shading Mode"},"sceneLighting":true,"audioPlay":false,"sceneViewState":{"showFog":true,"showMaterialUpdate":false,"showSkybox":true,"showFlares":true,"showImageEffects":true,"showParticleSystems":true},"in2DMode":false,"pivot":{"x":-2.5107803344726564,"y":-2.364567756652832,"z":16.87738037109375},"rotation":{"x":0.11758222430944443,"y":-0.1259782463312149,"z":0.015017109923064709,"w":0.9849735498428345},"size":19.453554153442384,"orthographic":false}